pshmem/__init__.py
pshmem/_version.py
pshmem/batch.py
pshmem/locking.py
pshmem/registry.py
pshmem/shmem.py
pshmem/test.py
pshmem/utils.py
pshmem-1.3.1.dist-info/licenses/LICENSE
pshmem-1.3.1.dist-info/METADATA
pshmem-1.3.1.dist-info/WHEEL
pshmem-1.3.1.dist-info/top_level.txt
pshmem-1.3.1.dist-info/RECORD
