Metadata-Version: 2.4
Name: pshmem
Version: 1.3.1
Summary: Parallel shared memory and locking with MPI
Maintainer-email: Theodore Kisner <tskisner.public@gmail.com>
Project-URL: Source, https://github.com/tskisner/pshmem
Project-URL: Issue Tracker, https://github.com/tskisner/pshmem/issues
Classifier: Development Status :: 4 - Beta
Classifier: License :: OSI Approved :: BSD License
Classifier: Programming Language :: Python
Classifier: Programming Language :: Python :: 3
Classifier: Programming Language :: Python :: 3.9
Classifier: Programming Language :: Python :: 3.10
Classifier: Programming Language :: Python :: 3.11
Classifier: Programming Language :: Python :: 3.12
Classifier: Programming Language :: Python :: 3.13
Classifier: Topic :: Software Development :: Libraries
Requires-Python: >=3.9
License-File: LICENSE
Requires-Dist: numpy
Provides-Extra: mpi
Requires-Dist: mpi4py; extra == "mpi"
Dynamic: license-file
